LICENSE
MANIFEST.in
README.rst
pyproject.toml
setup.cfg
setup.py
universaldjango/__init__.py
universaldjango/admin.py
universaldjango/apps.py
universaldjango/models.py
universaldjango/test.py
universaldjango/tests.py
universaldjango/views.py
universaldjango.egg-info/PKG-INFO
universaldjango.egg-info/SOURCES.txt
universaldjango.egg-info/dependency_links.txt
universaldjango.egg-info/requires.txt
universaldjango.egg-info/top_level.txt
universaldjango/migrations/0001_initial.py
universaldjango/migrations/__init__.py